toolla/__init__.py
toolla/chat.py
toolla/utils.py
toolla-0.0.2.dist-info/METADATA
toolla-0.0.2.dist-info/WHEEL
toolla-0.0.2.dist-info/licenses/LICENSE.txt
toolla-0.0.2.dist-info/RECORD
