Metadata-Version: 2.3
Name: toolla
Version: 0.0.2
Summary: Tool utilities for language models
Project-URL: Homepage, https://github.com/joorjeh/toolla
Project-URL: Issues, https://github.com/joorjeh/toolla/issues
Author-email: George Balch <george.balch@proton.me>
License-Expression: MIT
License-File: LICENSE.txt
Classifier: Operating System :: OS Independent
Classifier: Programming Language :: Python :: 3
Requires-Python: >=3.8
Requires-Dist: anthropic>=0.31.2
